water_pipe/__init__.py
water_pipe/__version__.py
water_pipe/base.py
water_pipe/channel.py
water_pipe/db_csv.py
water_pipe/db_excel.py
water_pipe/db_greenplum.py
water_pipe/db_hive.py
water_pipe/db_impala.py
water_pipe/db_mysql.py
water_pipe/db_postgres.py
water_pipe/test.py
water_pipe-0.0.3.dist-info/LICENSE
water_pipe-0.0.3.dist-info/METADATA
water_pipe-0.0.3.dist-info/WHEEL
water_pipe-0.0.3.dist-info/top_level.txt
water_pipe-0.0.3.dist-info/RECORD
